fake_footballer/__init__.py
fake_footballer/data.py
fake_footballer/footballer_gen.py
fake_footballer/one_club_gen.py
fake_footballer/to_do.py
fakefootballer/__init__.py
fakefootballer/data.py
fakefootballer/footballer_gen.py
footballfakedata-1.0.dist-info/METADATA
footballfakedata-1.0.dist-info/WHEEL
footballfakedata-1.0.dist-info/top_level.txt
footballfakedata-1.0.dist-info/RECORD
