Metadata-Version: 2.1
Name: footballfakedata
Version: 1.0
Summary: A package to generate fake footballer data
Home-page: UNKNOWN
Author: Marek Zarzycki
Author-email: contact@mazarzycki.com
License: UNKNOWN
Platform: UNKNOWN
Requires-Dist: pandas
